{
  "analysis_status": "passed",
  "blocker_count": 0,
  "blockers": [],
  "metrics_rows": 3000,
  "validation_rows": 10,
  "first_train_loss": 9.869211,
  "last_train_loss": 3.029707,
  "min_train_loss": 1.705493,
  "max_train_loss": 9.869211,
  "first_validation_loss": 9.028253,
  "last_validation_loss": 8.341638,
  "min_validation_loss": 8.230417,
  "max_validation_loss": 9.028253,
  "validation_loss_range": 0.797835,
  "validation_loss_population_stddev": 0.228388,
  "final_train_loss": 3.029707,
  "final_validation_loss": 8.341638,
  "validation_unique_doc_count": 15,
  "validation_prefix_only_risk": false,
  "train_loss_direction_first_to_last": "down",
  "validation_loss_direction_first_to_last": "down",
  "comparison_vs_5gb_1000_final_train_loss_delta": -0.130975,
  "comparison_vs_5gb_1000_final_validation_loss_delta": -0.872778,
  "comparison_vs_5gb_1000_final_train_loss": 3.160682,
  "comparison_vs_5gb_1000_final_validation_loss": 9.214416,
  "recommendation": "Proceed to MVP-27.B for next-stage experiment route selection. The 3000-step run improves validation measurement and final validation loss versus the 5GB 1000-step baseline, but do not jump directly to 10000-step; compare a bounded 5GB 5000-step option against technical experiments such as AdamW vs Muon, context length 1024, SDPA/FlashAttention profiling, and B200 scale planning."
}
